ngram_trie-1.2.6.dist-info/METADATA
ngram_trie-1.2.6.dist-info/WHEEL
ngram_trie/__init__.py
ngram_trie/__init__.pyi
ngram_trie/py.typed
ngram_trie/ngram_trie.cpython-312-x86_64-linux-gnu.so
ngram_trie-1.2.6.dist-info/RECORD
