Metadata-Version: 2.4
Name: ngram-trie
Version: 1.2.6
Summary: A Rust-based n-gram trie library for Python
Author: Botond Lovász
Author-email: botilovasz@gmail.com
Maintainer-email: Botond Lovász <botilovasz@gmail.com>
License: MIT
Requires-Python: >=3.6
Project-URL: Repository, https://github.com/behappiness/ngram-trie
